ais/__init__.py
ais/aco.py
ais/core.py
ais/ga.py
ais_toolkit_rohan-0.1.0.dist-info/METADATA
ais_toolkit_rohan-0.1.0.dist-info/WHEEL
ais_toolkit_rohan-0.1.0.dist-info/top_level.txt
ais_toolkit_rohan-0.1.0.dist-info/RECORD
