Metadata-Version: 2.4
Name: ais-toolkit-rohan
Version: 0.1.0
Summary: AIS, Genetic Algorithm, and Ant Colony Optimization toolkit
Author: Rohan Kaitake
Author-email: your_email@example.com
Classifier: Programming Language :: Python :: 3
Classifier: License :: OSI Approved :: MIT License
Classifier: Operating System :: OS Independent
Requires-Python: >=3.6
Requires-Dist: numpy
Requires-Dist: deap
Dynamic: author
Dynamic: author-email
Dynamic: classifier
Dynamic: requires-dist
Dynamic: requires-python
Dynamic: summary
